arku/__init__.py
arku/cli.py
arku/connections.py
arku/constants.py
arku/cron.py
arku/jobs.py
arku/logs.py
arku/parser.py
arku/typing.py
arku/utils.py
arku/worker.py
arku-1.0.0rc5.dist-info/LICENSE
arku-1.0.0rc5.dist-info/METADATA
arku-1.0.0rc5.dist-info/WHEEL
arku-1.0.0rc5.dist-info/entry_points.txt
arku-1.0.0rc5.dist-info/top_level.txt
arku-1.0.0rc5.dist-info/RECORD
