Metadata-Version: 2.1
Name: arku
Version: 1.0.0rc5
Summary: Fast job queuing and RPC in Python with asyncio and Redis
Home-page: https://github.com/targetaidev/arku
Author: TargetAI Ltd.
Author-email: dev@targetai.kz
License: MIT
Project-URL: Documentation, https://arku.readthedocs.io
Project-URL: Code, https://github.com/targetaidev/arku
Project-URL: Issues, https://github.com/targetaidev/arku/issues
Classifier: Development Status :: 4 - Beta
Classifier: Environment :: Console
Classifier: Framework :: AsyncIO
Classifier: Intended Audience :: Developers
Classifier: Intended Audience :: Information Technology
Classifier: Intended Audience :: System Administrators
Classifier: License :: OSI Approved :: MIT License
Classifier: Operating System :: Unix
Classifier: Operating System :: POSIX :: Linux
Classifier: Programming Language :: Python
Classifier: Programming Language :: Python :: 3
Classifier: Programming Language :: Python :: 3 :: Only
Classifier: Programming Language :: Python :: 3.8
Classifier: Programming Language :: Python :: 3.9
Classifier: Topic :: Internet
Classifier: Topic :: Software Development :: Libraries :: Python Modules
Classifier: Topic :: System :: Clustering
Classifier: Topic :: System :: Distributed Computing
Classifier: Topic :: System :: Monitoring
Classifier: Topic :: System :: Systems Administration
Requires-Python: >=3.8,<4
License-File: LICENSE
Requires-Dist: click <9,>=6.7
Requires-Dist: redis <6,>=4.2
Provides-Extra: dev
Requires-Dist: flake8-quotes ==3.3.2 ; extra == 'dev'
Requires-Dist: flake8 ==6.1.0 ; extra == 'dev'
Requires-Dist: isort ==5.12.0 ; extra == 'dev'
Requires-Dist: msgpack ==1.0.5 ; extra == 'dev'
Requires-Dist: watchgod >=0.8.2 ; extra == 'dev'
Provides-Extra: doc
Requires-Dist: docutils ==0.14 ; extra == 'doc'
Requires-Dist: pygments ==2.7.4 ; extra == 'doc'
Requires-Dist: sphinx ==2.0.1 ; extra == 'doc'
Requires-Dist: sphinxcontrib-websupport ==1.1.0 ; extra == 'doc'
Provides-Extra: test
Requires-Dist: coverage ==7.3.1 ; extra == 'test'
Requires-Dist: dirty-equals ==0.6.0 ; extra == 'test'
Requires-Dist: pytest-aiohttp ==0.3.0 ; extra == 'test'
Requires-Dist: pytest-cov ==2.8.1 ; extra == 'test'
Requires-Dist: pytest-mock ==3 ; extra == 'test'
Requires-Dist: pytest-sugar ==0.9.2 ; extra == 'test'
Requires-Dist: pytest-timeout ==1.3.3 ; extra == 'test'
Requires-Dist: pytest ==5.3.5 ; extra == 'test'
